amaia_core/__init__.py
amaia_core-0.0.1.dist-info/METADATA
amaia_core-0.0.1.dist-info/WHEEL
amaia_core-0.0.1.dist-info/top_level.txt
amaia_core-0.0.1.dist-info/RECORD
