Metadata-Version: 2.4
Name: amaia-core
Version: 0.0.1
Summary: AMAIA
Author-email: Jacob Kahn <jacobkahn1@gmail.com>
